pyClockTower/__init__.py
pyClockTower/aircom.py
pyClockTower/siteinfo.py
pyClockTower/sitelocation.py
pyClockTower/sitemapping.py
pyClockTower-1.0.0.dist-info/METADATA
pyClockTower-1.0.0.dist-info/WHEEL
pyClockTower-1.0.0.dist-info/top_level.txt
pyClockTower-1.0.0.dist-info/RECORD
