Metadata-Version: 2.1
Name: pyClockTower
Version: 1.0.0
Summary: A module that allows the user to check the status and attributes of a website
Home-page: UNKNOWN
Author: Seaver Olson
Author-email: Sjolson007@gmail.com
License: MIT
Platform: UNKNOWN
